yemot_flow/__init__.py
yemot_flow/actions.py
yemot_flow/call.py
yemot_flow/call.pyi
yemot_flow/flow.py
yemot_flow/py.typed
yemot_flow/utils.py
yemot_flow-0.2.20.dist-info/METADATA
yemot_flow-0.2.20.dist-info/WHEEL
yemot_flow-0.2.20.dist-info/entry_points.txt
yemot_flow-0.2.20.dist-info/RECORD
