Metadata-Version: 2.4
Name: yemot-flow
Version: 0.2.20
Summary: Modern async/await Python IVR framework for Yemot HaMashiach - Simple as Node.js yemot-router2
Project-URL: Homepage, https://github.com/davidTheDeveloperY/yemot-flow
Project-URL: Repository, https://github.com/davidTheDeveloperY/yemot-flow
Project-URL: Documentation, https://github.com/davidTheDeveloperY/yemot-flow#readme
Project-URL: Issues, https://github.com/davidTheDeveloperY/yemot-flow/issues
Project-URL: Changelog, https://github.com/davidTheDeveloperY/yemot-flow/releases
Project-URL: Examples, https://github.com/davidTheDeveloperY/yemot-flow/tree/master/examples
Author-email: davidTheDeveloper <dev@code-chai.com>
License: MIT
Keywords: async,flow,hamashiach,ivr,telephony,yemot
Classifier: Development Status :: 4 - Beta
Classifier: Framework :: AsyncIO
Classifier: Framework :: FastAPI
Classifier: Framework :: Flask
Classifier: Intended Audience :: Developers
Classifier: License :: OSI Approved :: MIT License
Classifier: Programming Language :: Python :: 3
Classifier: Programming Language :: Python :: 3.11
Classifier: Programming Language :: Python :: 3.12
Classifier: Programming Language :: Python :: 3.13
Classifier: Topic :: Communications :: Telephony
Classifier: Topic :: Software Development :: Libraries :: Python Modules
Requires-Python: >=3.11
Requires-Dist: flask>=2.3
